{
  "_class": "group",
  "do_objectID": "F8684BDD-91FB-416D-813F-5A1CE41340BC",
  "exportOptions": {
    "_class": "exportOptions",
    "exportFormats": [
    ],
    "includedLayerIds": [
    ],
    "layerOptions": 0,
    "shouldTrim": false
  },
  "frame": {
    "_class": "rect",
    "constrainProportions": true,
    "height": 36,
    "width": 36,
    "x": 2,
    "y": 2
  },
  "hasClickThrough": false,
  "isFlippedHorizontal": false,
  "isFlippedVertical": false,
  "isLocked": false,
  "isVisible": true,
  "layerListExpandedType": 0,
  "layers": [
    {
      "class": "group",
      "id": "B4EB2B8E-6C97-4638-8FF5-6D5FBB1FFA34"
    },
    {
      "class": "group",
      "id": "EE9D7C6C-D4C3-4C96-A302-E20AD97A0332"
    }
  ],
  "name": "Group 17",
  "nameIsFixed": false,
  "resizingConstraint": 63,
  "resizingType": 0,
  "rotation": 0,
  "shouldBreakMaskChain": false,
  "style": {
    "_class": "style",
    "endDecorationType": 0,
    "miterLimit": 10,
    "startDecorationType": 0
  }
}