{
  "_class": "shapeGroup",
  "clippingMaskMode": 0,
  "do_objectID": "8636CC6E-D20D-4A3F-8369-89FF430D58F0",
  "exportOptions": {
    "_class": "exportOptions",
    "exportFormats": [
    ],
    "includedLayerIds": [
    ],
    "layerOptions": 0,
    "shouldTrim": false
  },
  "frame": {
    "_class": "rect",
    "constrainProportions": false,
    "height": 19.92907801418437,
    "width": 19.9290780141844,
    "x": 2,
    "y": 2.000000000000014
  },
  "hasClickThrough": false,
  "hasClippingMask": false,
  "isFlippedHorizontal": false,
  "isFlippedVertical": false,
  "isLocked": false,
  "isVisible": true,
  "layerListExpandedType": 1,
  "layers": [
    {
      "class": "shapePath",
      "id": "33092DC2-03C6-4793-88E5-30ED1BF8E941"
    },
    {
      "class": "shapePath",
      "id": "401DCF90-AE99-4185-92ED-4A1A02548B9E"
    },
    {
      "class": "oval",
      "id": "83C0A6C0-A153-4204-97FA-B78A855E1538"
    }
  ],
  "name": "Glyph",
  "nameIsFixed": true,
  "originalObjectID": "71681ECD-AB1C-4B21-A5FB-9F3030FD4270",
  "resizingConstraint": 63,
  "resizingType": 0,
  "rotation": 0,
  "shouldBreakMaskChain": false,
  "style": {
    "_class": "style",
    "endDecorationType": 0,
    "fills": [
      {
        "_class": "fill",
        "color": {
          "_class": "color",
          "alpha": 0.95,
          "blue": 1,
          "green": 1,
          "red": 1
        },
        "fillType": 0,
        "gradient": {
          "_class": "gradient",
          "elipseLength": 0,
          "from": "{0.15267081477050143, 0.1403300998306744}",
          "gradientType": 0,
          "stops": [
            {
              "_class": "gradientStop",
              "color": {
                "_class": "color",
                "alpha": 1,
                "blue": 1,
                "green": 1,
                "red": 1
              },
              "position": 0
            },
            {
              "_class": "gradientStop",
              "color": {
                "_class": "color",
                "alpha": 1,
                "blue": 0,
                "green": 0,
                "red": 0
              },
              "position": 1
            }
          ],
          "to": "{0.84732918522949863, 0.85966990016932554}"
        },
        "isEnabled": true,
        "noiseIndex": 0,
        "noiseIntensity": 0,
        "patternFillType": 1,
        "patternTileScale": 1
      }
    ],
    "miterLimit": 10,
    "startDecorationType": 0
  },
  "windingRule": 0
}